pyup_django/__init__.py
pyup_django/admin.py
pyup_django/apps.py
pyup_django/models.py
pyup_django/settings.py
pyup_django/templates/insecure.html
pyup_django/templates/admin/base.html
pyup_django-0.4.0.dist-info/DESCRIPTION.rst
pyup_django-0.4.0.dist-info/METADATA
pyup_django-0.4.0.dist-info/RECORD
pyup_django-0.4.0.dist-info/WHEEL
pyup_django-0.4.0.dist-info/metadata.json
pyup_django-0.4.0.dist-info/top_level.txt
